README.md
setup.py
attrezzo/__init__.py
attrezzo.egg-info/PKG-INFO
attrezzo.egg-info/SOURCES.txt
attrezzo.egg-info/dependency_links.txt
attrezzo.egg-info/top_level.txt